fptools/__init__.py
fptools/__main__.py
fptools-1.0.dist-info/DESCRIPTION.rst
fptools-1.0.dist-info/METADATA
fptools-1.0.dist-info/RECORD
fptools-1.0.dist-info/WHEEL
fptools-1.0.dist-info/metadata.json
fptools-1.0.dist-info/top_level.txt
