Metadata-Version: 2.0
Name: fptools
Version: 1.0
Summary: A pure python implementation of the FP-growth and FPmax algorithm for mining frequent itemsets (patterns).
Home-page: https://bitbucket.org/harenbergsd/frequent-itemset-mining
Author: Steve Harenberg
Author-email: harenbergsd@gmail.com
License: CC0
Download-URL: https://bitbucket.org/harenbergsd/frequent-itemset-mining/get/v1.0.zip
Keywords: frequent,pattern,itemset,mining,fpgrowth,fpmax
Platform: UNKNOWN
